{
    "detection": [
        {
            "det_cat": 6,
            "det_name": "Robot",
            "det_x": 0.8727499842643738,
            "det_y": 0.29112499952316284,
            "det_w": 0.09849999845027924,
            "det_h": 0.3987500071525574,
            "det_score": 0.3047407865524292
        },
        {
            "det_cat": 5,
            "det_name": "Printer3D",
            "det_x": 0.5895000100135803,
            "det_y": 0.5716249942779541,
            "det_w": 0.12333333492279053,
            "det_h": 0.2917500138282776,
            "det_score": 0.46136489510536194
        },
        {
            "det_cat": 6,
            "det_name": "Robot",
            "det_x": 0.22283333539962769,
            "det_y": 0.18337500095367432,
            "det_w": 0.4426666796207428,
            "det_h": 0.36675000190734863,
            "det_score": 0.49129369854927063
        },
        {
            "det_cat": 5,
            "det_name": "Printer3D",
            "det_x": 0.5891666412353516,
            "det_y": 0.5734999775886536,
            "det_w": 0.1106666699051857,
            "det_h": 0.18400000035762787,
            "det_score": 0.5963302850723267
        },
        {
            "det_cat": 5,
            "det_name": "Printer3D",
            "det_x": 0.4659166634082794,
            "det_y": 0.5652499794960022,
            "det_w": 0.16616666316986084,
            "det_h": 0.34049999713897705,
            "det_score": 0.6269659996032715
        },
        {
            "det_cat": 5,
            "det_name": "Printer3D",
            "det_x": 0.46416667103767395,
            "det_y": 0.5702499747276306,
            "det_w": 0.15399999916553497,
            "det_h": 0.1914999932050705,
            "det_score": 0.6673462986946106
        },
        {
            "det_cat": 6,
            "det_name": "Robot",
            "det_x": 0.734333336353302,
            "det_y": 0.5534999966621399,
            "det_w": 0.2853333353996277,
            "det_h": 0.8930000066757202,
            "det_score": 0.7519785761833191
        }
    ],
    "img_path": "/Users/kritkorns/Mike/Jacob/AdvancedProject2/rawdata/machine/images/IMG_0421.JPG",
    "img_name": "IMG_0421",
    "img_id": "6d3084e28d6057f706d4c7bd628a2d6b530e974f63f19a25fdb98afafd28e7bb"
}