{
    "detection": [
        {
            "det_cat": 4,
            "det_name": "MillingMachine",
            "det_x": 0.15666666626930237,
            "det_y": 0.5643749833106995,
            "det_w": 0.20033332705497742,
            "det_h": 0.26225000619888306,
            "det_score": 0.26830172538757324
        },
        {
            "det_cat": 4,
            "det_name": "MillingMachine",
            "det_x": 0.47325000166893005,
            "det_y": 0.6841250061988831,
            "det_w": 0.18283332884311676,
            "det_h": 0.24324999749660492,
            "det_score": 0.3209196925163269
        },
        {
            "det_cat": 4,
            "det_name": "MillingMachine",
            "det_x": 0.7315833568572998,
            "det_y": 0.6244999766349792,
            "det_w": 0.15449999272823334,
            "det_h": 0.47350001335144043,
            "det_score": 0.4193321168422699
        },
        {
            "det_cat": 0,
            "det_name": "BandSaw",
            "det_x": 0.5175833106040955,
            "det_y": 0.7642499804496765,
            "det_w": 0.19816666841506958,
            "det_h": 0.38449999690055847,
            "det_score": 0.5117332339286804
        },
        {
            "det_cat": 4,
            "det_name": "MillingMachine",
            "det_x": 0.5398333072662354,
            "det_y": 0.6198750138282776,
            "det_w": 0.23866666853427887,
            "det_h": 0.38475000858306885,
            "det_score": 0.5301961302757263
        },
        {
            "det_cat": 0,
            "det_name": "BandSaw",
            "det_x": 0.5259166955947876,
            "det_y": 0.7711250185966492,
            "det_w": 0.2671666741371155,
            "det_h": 0.2667500078678131,
            "det_score": 0.669823408126831
        }
    ],
    "img_path": "/Users/kritkorns/Mike/Jacob/AdvancedProject2/rawdata/machine/images/IMG_0809.JPG",
    "img_name": "IMG_0809",
    "img_id": "fd623592d8b502ace980389ffa2857835e3e5e1f3f56aa2880260d53b8e9ff57"
}