{
    "detection": [
        {
            "det_cat": 5,
            "det_name": "Printer3D",
            "det_x": 0.6397500038146973,
            "det_y": 0.503125011920929,
            "det_w": 0.20683333277702332,
            "det_h": 0.2772499918937683,
            "det_score": 0.30055803060531616
        },
        {
            "det_cat": 6,
            "det_name": "Robot",
            "det_x": 0.8573333621025085,
            "det_y": 0.5,
            "det_w": 0.2853333353996277,
            "det_h": 1.0,
            "det_score": 0.4407176077365875
        },
        {
            "det_cat": 5,
            "det_name": "Printer3D",
            "det_x": 0.6335833072662354,
            "det_y": 0.5074999928474426,
            "det_w": 0.15316666662693024,
            "det_h": 0.3815000057220459,
            "det_score": 0.5749126076698303
        },
        {
            "det_cat": 5,
            "det_name": "Printer3D",
            "det_x": 0.4635833203792572,
            "det_y": 0.4860000014305115,
            "det_w": 0.23716667294502258,
            "det_h": 0.3799999952316284,
            "det_score": 0.595719575881958
        },
        {
            "det_cat": 5,
            "det_name": "Printer3D",
            "det_x": 0.468583345413208,
            "det_y": 0.4962500035762787,
            "det_w": 0.23416666686534882,
            "det_h": 0.22750000655651093,
            "det_score": 0.6164618134498596
        },
        {
            "det_cat": 5,
            "det_name": "Printer3D",
            "det_x": 0.6379166841506958,
            "det_y": 0.5117499828338623,
            "det_w": 0.16883333027362823,
            "det_h": 0.18649999797344208,
            "det_score": 0.6605529189109802
        }
    ],
    "img_path": "/Users/kritkorns/Mike/Jacob/AdvancedProject2/rawdata/machine/images/IMG_0395.JPG",
    "img_name": "IMG_0395",
    "img_id": "8297766ac30d8629987c36aee5c6d8b947e85b6993fda52257d6cf2308397fd5"
}