{
    "detection": [
        {
            "det_cat": 5,
            "det_name": "Printer3D",
            "det_x": 0.20624999701976776,
            "det_y": 0.046875,
            "det_w": 0.09983333200216293,
            "det_h": 0.09375,
            "det_score": 0.2650013864040375
        },
        {
            "det_cat": 5,
            "det_name": "Printer3D",
            "det_x": 0.19366666674613953,
            "det_y": 0.03087499924004078,
            "det_w": 0.09700000286102295,
            "det_h": 0.06174999848008156,
            "det_score": 0.2914668619632721
        },
        {
            "det_cat": 6,
            "det_name": "Robot",
            "det_x": 0.10249999910593033,
            "det_y": 0.29787498712539673,
            "det_w": 0.20499999821186066,
            "det_h": 0.49524998664855957,
            "det_score": 0.2921698987483978
        },
        {
            "det_cat": 5,
            "det_name": "Printer3D",
            "det_x": 0.2823333442211151,
            "det_y": 0.02762500010430813,
            "det_w": 0.08366666734218597,
            "det_h": 0.05525000020861626,
            "det_score": 0.31422269344329834
        },
        {
            "det_cat": 6,
            "det_name": "Robot",
            "det_x": 0.09308333694934845,
            "det_y": 0.2915000021457672,
            "det_w": 0.1574999988079071,
            "det_h": 0.39899998903274536,
            "det_score": 0.38849231600761414
        },
        {
            "det_cat": 5,
            "det_name": "Printer3D",
            "det_x": 0.20991666615009308,
            "det_y": 0.03200000151991844,
            "det_w": 0.09350000321865082,
            "det_h": 0.06400000303983688,
            "det_score": 0.4034467041492462
        },
        {
            "det_cat": 6,
            "det_name": "Robot",
            "det_x": 0.30158331990242004,
            "det_y": 0.38874998688697815,
            "det_w": 0.11550000309944153,
            "det_h": 0.3440000116825104,
            "det_score": 0.6970667839050293
        }
    ],
    "img_path": "/Users/kritkorns/Mike/Jacob/AdvancedProject2/rawdata/machine/images/IMG_0541.JPG",
    "img_name": "IMG_0541",
    "img_id": "c7371069a91c3d243e0cfc642fe040b591ab4aff8ee9592ebef8e061bf6c6e94"
}