{
    "detection": [
        {
            "det_cat": 5,
            "det_name": "Printer3D",
            "det_x": 0.6725000143051147,
            "det_y": 0.4516249895095825,
            "det_w": 0.06800000369548798,
            "det_h": 0.17874999344348907,
            "det_score": 0.2677302062511444
        },
        {
            "det_cat": 5,
            "det_name": "Printer3D",
            "det_x": 0.6100000143051147,
            "det_y": 0.44062501192092896,
            "det_w": 0.07999999821186066,
            "det_h": 0.20925000309944153,
            "det_score": 0.30030348896980286
        },
        {
            "det_cat": 5,
            "det_name": "Printer3D",
            "det_x": 0.6708333492279053,
            "det_y": 0.4518750011920929,
            "det_w": 0.0533333346247673,
            "det_h": 0.1107499971985817,
            "det_score": 0.30920934677124023
        },
        {
            "det_cat": 5,
            "det_name": "Printer3D",
            "det_x": 0.6076666712760925,
            "det_y": 0.44600000977516174,
            "det_w": 0.07366666942834854,
            "det_h": 0.1120000034570694,
            "det_score": 0.31841450929641724
        },
        {
            "det_cat": 6,
            "det_name": "Robot",
            "det_x": 0.2709999978542328,
            "det_y": 0.3501250147819519,
            "det_w": 0.15166667103767395,
            "det_h": 0.3712500035762787,
            "det_score": 0.6785148978233337
        }
    ],
    "img_path": "/Users/kritkorns/Mike/Jacob/AdvancedProject2/rawdata/machine/images/IMG_0406.JPG",
    "img_name": "IMG_0406",
    "img_id": "81e1fd83237d36781815a987c124dfe5ff1003d0ecc548ffd70135ec3056460b"
}