{
    "detection": [
        {
            "det_cat": 24,
            "det_name": "Robot_UpperArm",
            "det_x": 0.6258333325386047,
            "det_y": 0.30550000071525574,
            "det_w": 0.05900000035762787,
            "det_h": 0.08399999886751175,
            "det_score": 0.26393142342567444
        },
        {
            "det_cat": 24,
            "det_name": "Robot_UpperArm",
            "det_x": 0.6215000152587891,
            "det_y": 0.32199999690055847,
            "det_w": 0.10400000214576721,
            "det_h": 0.18000000715255737,
            "det_score": 0.4055408835411072
        },
        {
            "det_cat": 23,
            "det_name": "Robot_Head",
            "det_x": 0.6259999871253967,
            "det_y": 0.382999986410141,
            "det_w": 0.11133333295583725,
            "det_h": 0.06549999862909317,
            "det_score": 0.48690658807754517
        },
        {
            "det_cat": 24,
            "det_name": "Robot_UpperArm",
            "det_x": 0.6206666827201843,
            "det_y": 0.30812498927116394,
            "det_w": 0.08133333176374435,
            "det_h": 0.12224999815225601,
            "det_score": 0.488352507352829
        },
        {
            "det_cat": 23,
            "det_name": "Robot_Head",
            "det_x": 0.6294999718666077,
            "det_y": 0.3930000066757202,
            "det_w": 0.1446666717529297,
            "det_h": 0.08550000190734863,
            "det_score": 0.6400753259658813
        },
        {
            "det_cat": 22,
            "det_name": "Robot_BaseArm",
            "det_x": 0.6261666417121887,
            "det_y": 0.5448750257492065,
            "det_w": 0.1589999943971634,
            "det_h": 0.4322499930858612,
            "det_score": 0.6454277038574219
        }
    ],
    "img_path": "/data/home/mike/advanced_project2/dataset/machines/IMG_0207.JPG",
    "img_name": "IMG_0207",
    "img_id": "f52bdb49a10bca60462b33bbbd94867ffb10618a984745f09001da39578bfa06"
}