{
    "detection": [
        {
            "det_cat": 23,
            "det_name": "Robot_Head",
            "det_x": 0.6865000128746033,
            "det_y": 0.5090000033378601,
            "det_w": 0.07966666668653488,
            "det_h": 0.07850000262260437,
            "det_score": 0.2576777935028076
        },
        {
            "det_cat": 24,
            "det_name": "Robot_UpperArm",
            "det_x": 0.546583354473114,
            "det_y": 0.398624986410141,
            "det_w": 0.36783334612846375,
            "det_h": 0.16474999487400055,
            "det_score": 0.34849631786346436
        },
        {
            "det_cat": 22,
            "det_name": "Robot_BaseArm",
            "det_x": 0.5016666650772095,
            "det_y": 0.7024999856948853,
            "det_w": 0.35366666316986084,
            "det_h": 0.5950000286102295,
            "det_score": 0.44973137974739075
        },
        {
            "det_cat": 1,
            "det_name": "Printer3D_Filament",
            "det_x": 0.9665833115577698,
            "det_y": 0.859624981880188,
            "det_w": 0.04349999874830246,
            "det_h": 0.07275000214576721,
            "det_score": 0.5354503393173218
        },
        {
            "det_cat": 23,
            "det_name": "Robot_Head",
            "det_x": 0.687250018119812,
            "det_y": 0.5131250023841858,
            "det_w": 0.12383333593606949,
            "det_h": 0.09274999797344208,
            "det_score": 0.6357795596122742
        },
        {
            "det_cat": 24,
            "det_name": "Robot_UpperArm",
            "det_x": 0.5383333563804626,
            "det_y": 0.40575000643730164,
            "det_w": 0.4309999942779541,
            "det_h": 0.24199999868869781,
            "det_score": 0.7306908965110779
        }
    ],
    "img_path": "/data/home/mike/advanced_project2/dataset/machines/IMG_0352.JPG",
    "img_name": "IMG_0352",
    "img_id": "92b9d54436d8ad13d2738866bd2ac0d6a0a5198b21d8bc236137ff79a0b9e13c"
}