{
    "detection": [
        {
            "det_cat": 24,
            "det_name": "Robot_UpperArm",
            "det_x": 0.2070000022649765,
            "det_y": 0.44325000047683716,
            "det_w": 0.1863333284854889,
            "det_h": 0.11900000274181366,
            "det_score": 0.26180702447891235
        },
        {
            "det_cat": 22,
            "det_name": "Robot_BaseArm",
            "det_x": 0.765500009059906,
            "det_y": 0.6466249823570251,
            "det_w": 0.0689999982714653,
            "det_h": 0.3642500042915344,
            "det_score": 0.27936360239982605
        },
        {
            "det_cat": 24,
            "det_name": "Robot_UpperArm",
            "det_x": 0.33033332228660583,
            "det_y": 0.44212499260902405,
            "det_w": 0.5723333358764648,
            "det_h": 0.4267500042915344,
            "det_score": 0.2847885489463806
        },
        {
            "det_cat": 0,
            "det_name": "Printer3D_Body",
            "det_x": 0.6834166646003723,
            "det_y": 0.7114999890327454,
            "det_w": 0.05316666513681412,
            "det_h": 0.12549999356269836,
            "det_score": 0.31083670258522034
        },
        {
            "det_cat": 0,
            "det_name": "Printer3D_Body",
            "det_x": 0.6826666593551636,
            "det_y": 0.7147499918937683,
            "det_w": 0.0676666647195816,
            "det_h": 0.17399999499320984,
            "det_score": 0.31215521693229675
        },
        {
            "det_cat": 22,
            "det_name": "Robot_BaseArm",
            "det_x": 0.7578333616256714,
            "det_y": 0.6538749933242798,
            "det_w": 0.10499999672174454,
            "det_h": 0.28575000166893005,
            "det_score": 0.3191736936569214
        },
        {
            "det_cat": 24,
            "det_name": "Robot_UpperArm",
            "det_x": 0.21016666293144226,
            "det_y": 0.4377500116825104,
            "det_w": 0.15733332931995392,
            "det_h": 0.06949999928474426,
            "det_score": 0.3312224745750427
        },
        {
            "det_cat": 22,
            "det_name": "Robot_BaseArm",
            "det_x": 0.20608332753181458,
            "det_y": 0.6050000190734863,
            "det_w": 0.16850000619888306,
            "det_h": 0.28700000047683716,
            "det_score": 0.3685518205165863
        },
        {
            "det_cat": 22,
            "det_name": "Robot_BaseArm",
            "det_x": 0.7637500166893005,
            "det_y": 0.6553750038146973,
            "det_w": 0.05183333158493042,
            "det_h": 0.2852500081062317,
            "det_score": 0.37414655089378357
        },
        {
            "det_cat": 24,
            "det_name": "Robot_UpperArm",
            "det_x": 0.718583345413208,
            "det_y": 0.6008750200271606,
            "det_w": 0.11649999767541885,
            "det_h": 0.2097499966621399,
            "det_score": 0.3786264657974243
        },
        {
            "det_cat": 24,
            "det_name": "Robot_UpperArm",
            "det_x": 0.4129999876022339,
            "det_y": 0.4456250071525574,
            "det_w": 0.2926666736602783,
            "det_h": 0.3472500145435333,
            "det_score": 0.3899329602718353
        },
        {
            "det_cat": 0,
            "det_name": "Printer3D_Body",
            "det_x": 0.6258333325386047,
            "det_y": 0.7072499990463257,
            "det_w": 0.06433333456516266,
            "det_h": 0.13600000739097595,
            "det_score": 0.42677661776542664
        },
        {
            "det_cat": 24,
            "det_name": "Robot_UpperArm",
            "det_x": 0.7162500023841858,
            "det_y": 0.5966249704360962,
            "det_w": 0.05249999836087227,
            "det_h": 0.1457500010728836,
            "det_score": 0.43302878737449646
        },
        {
            "det_cat": 24,
            "det_name": "Robot_UpperArm",
            "det_x": 0.36783334612846375,
            "det_y": 0.4494999945163727,
            "det_w": 0.4259999990463257,
            "det_h": 0.17599999904632568,
            "det_score": 0.5126577615737915
        },
        {
            "det_cat": 23,
            "det_name": "Robot_Head",
            "det_x": 0.5385000109672546,
            "det_y": 0.5868750214576721,
            "det_w": 0.05700000002980232,
            "det_h": 0.08025000244379044,
            "det_score": 0.52275151014328
        },
        {
            "det_cat": 1,
            "det_name": "Printer3D_Filament",
            "det_x": 0.5741666555404663,
            "det_y": 0.7276250123977661,
            "det_w": 0.03133333474397659,
            "det_h": 0.04475000128149986,
            "det_score": 0.5470207929611206
        },
        {
            "det_cat": 22,
            "det_name": "Robot_BaseArm",
            "det_x": 0.20900000631809235,
            "det_y": 0.6021249890327454,
            "det_w": 0.26466667652130127,
            "det_h": 0.3127500116825104,
            "det_score": 0.5663108229637146
        },
        {
            "det_cat": 22,
            "det_name": "Robot_BaseArm",
            "det_x": 0.3225833475589752,
            "det_y": 0.5688750147819519,
            "det_w": 0.15716665983200073,
            "det_h": 0.4177500009536743,
            "det_score": 0.5745375752449036
        },
        {
            "det_cat": 24,
            "det_name": "Robot_UpperArm",
            "det_x": 0.7159166932106018,
            "det_y": 0.5951250195503235,
            "det_w": 0.07716666907072067,
            "det_h": 0.18774999678134918,
            "det_score": 0.5973972678184509
        },
        {
            "det_cat": 23,
            "det_name": "Robot_Head",
            "det_x": 0.5397499799728394,
            "det_y": 0.5847499966621399,
            "det_w": 0.08550000190734863,
            "det_h": 0.05700000002980232,
            "det_score": 0.6011019349098206
        },
        {
            "det_cat": 23,
            "det_name": "Robot_Head",
            "det_x": 0.5409166812896729,
            "det_y": 0.5824999809265137,
            "det_w": 0.054499998688697815,
            "det_h": 0.04749999940395355,
            "det_score": 0.6057590246200562
        },
        {
            "det_cat": 24,
            "det_name": "Robot_UpperArm",
            "det_x": 0.3736666738986969,
            "det_y": 0.4388749897480011,
            "det_w": 0.4543333351612091,
            "det_h": 0.2932499945163727,
            "det_score": 0.6211604475975037
        },
        {
            "det_cat": 0,
            "det_name": "Printer3D_Body",
            "det_x": 0.6223333477973938,
            "det_y": 0.7056249976158142,
            "det_w": 0.07766667008399963,
            "det_h": 0.08974999934434891,
            "det_score": 0.633867621421814
        },
        {
            "det_cat": 0,
            "det_name": "Printer3D_Body",
            "det_x": 0.6869166493415833,
            "det_y": 0.7098749876022339,
            "det_w": 0.05849999934434891,
            "det_h": 0.06875000149011612,
            "det_score": 0.6550886631011963
        },
        {
            "det_cat": 0,
            "det_name": "Printer3D_Body",
            "det_x": 0.6825833320617676,
            "det_y": 0.7085000276565552,
            "det_w": 0.07716666907072067,
            "det_h": 0.09700000286102295,
            "det_score": 0.6640957593917847
        }
    ],
    "img_path": "/data/home/mike/advanced_project2/dataset/machines/IMG_0427.JPG",
    "img_name": "IMG_0427",
    "img_id": "81927c369addffffa9fc7d12e900a8a66ddf15b85a1041249c28422c6126a9d9"
}