{
    "detection": [
        {
            "det_cat": 23,
            "det_name": "Robot_Head",
            "det_x": 0.7681666612625122,
            "det_y": 0.38624998927116394,
            "det_w": 0.06233333423733711,
            "det_h": 0.06750000268220901,
            "det_score": 0.2738277018070221
        },
        {
            "det_cat": 24,
            "det_name": "Robot_UpperArm",
            "det_x": 0.5819166898727417,
            "det_y": 0.42112499475479126,
            "det_w": 0.04749999940395355,
            "det_h": 0.14675000309944153,
            "det_score": 0.28745996952056885
        },
        {
            "det_cat": 24,
            "det_name": "Robot_UpperArm",
            "det_x": 0.8514999747276306,
            "det_y": 0.2632499933242798,
            "det_w": 0.2906666696071625,
            "det_h": 0.2994999885559082,
            "det_score": 0.35115882754325867
        },
        {
            "det_cat": 23,
            "det_name": "Robot_Head",
            "det_x": 0.7727500200271606,
            "det_y": 0.382999986410141,
            "det_w": 0.07316666841506958,
            "det_h": 0.10400000214576721,
            "det_score": 0.4178854525089264
        },
        {
            "det_cat": 23,
            "det_name": "Robot_Head",
            "det_x": 0.7702500224113464,
            "det_y": 0.3871249854564667,
            "det_w": 0.05816666781902313,
            "det_h": 0.04324999824166298,
            "det_score": 0.4767962396144867
        },
        {
            "det_cat": 22,
            "det_name": "Robot_BaseArm",
            "det_x": 0.9428333044052124,
            "det_y": 0.40299999713897705,
            "det_w": 0.11433333158493042,
            "det_h": 0.565500020980835,
            "det_score": 0.5982541441917419
        },
        {
            "det_cat": 24,
            "det_name": "Robot_UpperArm",
            "det_x": 0.8363333344459534,
            "det_y": 0.28075000643730164,
            "det_w": 0.21466666460037231,
            "det_h": 0.21150000393390656,
            "det_score": 0.6080895662307739
        }
    ],
    "img_path": "/data/home/mike/advanced_project2/dataset/machines/IMG_0593.JPG",
    "img_name": "IMG_0593",
    "img_id": "f2d382092598f13a2b415ecb24cfc2e892f7ce7715dd719442688fd0478d3265"
}